etc/neutron/policy.d/bsn_plugin_policy.json
networking_bigswitch/__init__.py
networking_bigswitch/plugins/__init__.py
networking_bigswitch/plugins/bigswitch/README
networking_bigswitch/plugins/bigswitch/__init__.py
networking_bigswitch/plugins/bigswitch/bsn_service_plugin.py
networking_bigswitch/plugins/bigswitch/config.py
networking_bigswitch/plugins/bigswitch/constants.py
networking_bigswitch/plugins/bigswitch/dhcp_driver.py
networking_bigswitch/plugins/bigswitch/i18n.py
networking_bigswitch/plugins/bigswitch/plugin.py
networking_bigswitch/plugins/bigswitch/servermanager.py
networking_bigswitch/plugins/bigswitch/state_syncer.py
networking_bigswitch/plugins/bigswitch/utils.py
networking_bigswitch/plugins/bigswitch/vcsversion.py
networking_bigswitch/plugins/bigswitch/version.py
networking_bigswitch/plugins/bigswitch/agent/__init__.py
networking_bigswitch/plugins/bigswitch/agent/restproxy_agent.py
networking_bigswitch/plugins/bigswitch/db/__init__.py
networking_bigswitch/plugins/bigswitch/db/consistency_db.py
networking_bigswitch/plugins/bigswitch/db/network_template_db.py
networking_bigswitch/plugins/bigswitch/db/porttracker_db.py
networking_bigswitch/plugins/bigswitch/db/reachability_test_db.py
networking_bigswitch/plugins/bigswitch/db/tenant_policy_db.py
networking_bigswitch/plugins/bigswitch/db/migration/__init__.py
networking_bigswitch/plugins/bigswitch/db/migration/alembic_migrations/README
networking_bigswitch/plugins/bigswitch/db/migration/alembic_migrations/__init__.py
networking_bigswitch/plugins/bigswitch/db/migration/alembic_migrations/env.py
networking_bigswitch/plugins/bigswitch/db/migration/alembic_migrations/script.py.mako
networking_bigswitch/plugins/bigswitch/db/migration/alembic_migrations/versions/1086543dfc0f_update_column_type_for_testpath_result.py
networking_bigswitch/plugins/bigswitch/db/migration/alembic_migrations/versions/1ef57200f387_testpath_modify_uniq_constraint.py
networking_bigswitch-15.0.2.dist-info/AUTHORS
networking_bigswitch-15.0.2.dist-info/LICENSE
networking_bigswitch-15.0.2.dist-info/METADATA
networking_bigswitch-15.0.2.dist-info/WHEEL
networking_bigswitch-15.0.2.dist-info/entry_points.txt
networking_bigswitch-15.0.2.dist-info/pbr.json
networking_bigswitch-15.0.2.dist-info/top_level.txt
networking_bigswitch-15.0.2.dist-info/RECORD
