Metadata-Version: 2.1
Name: networking-bigswitch
Version: 15.0.2
Summary: Arista Networks CCF Plugin for OpenStack Networking
Home-page: http://www.arista.com/
Author: Arista Networks
Author-email: support@arista.com
License: UNKNOWN
Platform: UNKNOWN
Classifier: Environment :: OpenStack
Classifier: Intended Audience :: Information Technology
Classifier: Intended Audience :: System Administrators
Classifier: License :: OSI Approved :: Apache Software License
Classifier: Operating System :: POSIX :: Linux
Classifier: Programming Language :: Python
Classifier: Programming Language :: Python :: 2
Classifier: Programming Language :: Python :: 2.7
Classifier: Programming Language :: Python :: 3
Classifier: Programming Language :: Python :: 3.5
Classifier: Programming Language :: Python :: 3.6
Requires-Dist: SQLAlchemy (>=1.2.12)
Requires-Dist: WebOb (>=1.8.4)
Requires-Dist: alembic (>=1.0.0)
Requires-Dist: distro (>=1.3.0)
Requires-Dist: eventlet (>=0.24.1)
Requires-Dist: keystoneauth1 (>=3.11.1)
Requires-Dist: mock (>=2.0.0)
Requires-Dist: neutron (<16.0.0,>=15.0.0)
Requires-Dist: neutron-lib (>=1.22.0)
Requires-Dist: os-net-config (>=10.0.0)
Requires-Dist: oslo.i18n (>=3.22.1)
Requires-Dist: oslo.serialization (>=2.28.1)
Requires-Dist: oslo.utils (>=3.37.1)
Requires-Dist: oslo-config (>=6.7.0)
Requires-Dist: oslo-db (>=4.42.0)
Requires-Dist: oslo-log (>=3.40.1)
Requires-Dist: oslo-messaging (>=9.2.0)
Requires-Dist: oslo-service (>=1.33.0)
Requires-Dist: oslotest (>=3.7.0)
Requires-Dist: python-keystoneclient (>=3.18.0)
Requires-Dist: requests (>=2.18.4)
Requires-Dist: setuptools (>=18.5)
Requires-Dist: six (>=1.11.0)
